peewee_erd/__init__.py
peewee_erd/erd.dot
peewee_erd-0.1.3.dist-info/entry_points.txt
peewee_erd-0.1.3.dist-info/LICENSE
peewee_erd-0.1.3.dist-info/WHEEL
peewee_erd-0.1.3.dist-info/METADATA
peewee_erd-0.1.3.dist-info/RECORD
